ghtc/CHANGELOG.md
ghtc/__init__.py
ghtc/cli.py
ghtc/models.py
ghtc/overrides.py
ghtc/parser.py
ghtc/utils.py
ghtc-0.2.1.dist-info/LICENSE
ghtc-0.2.1.dist-info/METADATA
ghtc-0.2.1.dist-info/WHEEL
ghtc-0.2.1.dist-info/entry_points.txt
ghtc-0.2.1.dist-info/top_level.txt
ghtc-0.2.1.dist-info/RECORD
