Metadata-Version: 2.2
Name: ghtc
Version: 0.2.1
Summary: ghtc service
Home-page: https://git.meteo.fr/dsi-dev-ws/ghtc
Author: Fabien MARTY
Author-email: fabien.marty@meteo.fr
License: BSD 3
Requires-Python: >=3.6
License-File: LICENSE
Requires-Dist: typer
Requires-Dist: mfutil
Requires-Dist: GitPython==3.1.14
Requires-Dist: mflog
Dynamic: author
Dynamic: author-email
Dynamic: description
Dynamic: description-content-type
Dynamic: home-page
Dynamic: license
Dynamic: requires-dist
Dynamic: requires-python
Dynamic: summary
